lana-0.1.8.dist-info/METADATA
lana-0.1.8.dist-info/WHEEL
lana-0.1.8.dist-info/license_files/LICENSE
lana/__init__.py
lana/lana.cpython-39-darwin.so
lana-0.1.8.dist-info/RECORD
