Metadata-Version: 2.1
Name: lana
Version: 0.1.8
Classifier: Programming Language :: Rust
Classifier: Programming Language :: Python :: Implementation :: CPython
Classifier: Programming Language :: Python :: Implementation :: PyPy
License-File: LICENSE
Summary: Experimental Linear Algebra library written in Rust
Keywords: linear algebra
Author-email: Marco Salvalaggio <mar.salvalaggio@gmail.com>
Requires-Python: >=3.7
Project-URL: Repository, https://github.com/marcosalvalaggio/lana
